docs/conf.py
pycroglia/__init__.py
pycroglia/__main__.py
pycroglia/core/__init__.py
pycroglia/core/arclength.py
pycroglia/core/bounding_box.py
pycroglia/core/branch_analysis.py
pycroglia/core/centroid.py
pycroglia/core/clustering.py
pycroglia/core/connection.py
pycroglia/core/enums.py
pycroglia/core/erosion.py
pycroglia/core/filters.py
pycroglia/core/full_cell_analysis.py
pycroglia/core/labeled_cells.py
pycroglia/core/nearest_pixel.py
pycroglia/core/reorder.py
pycroglia/core/segmentation.py
pycroglia/core/territorial_volume.py
pycroglia/core/compute/__init__.py
pycroglia/core/compute/backend.py
pycroglia/core/compute/computable.py
pycroglia/core/compute/mp_pool.py
pycroglia/core/compute/pool.py
pycroglia/core/compute/qt_pool.py
pycroglia/core/compute/tests/__init__.py
pycroglia/core/compute/tests/unit/__init__.py
pycroglia/core/compute/tests/unit/test_mp_pool.py
pycroglia/core/compute/tests/unit/test_qt_pool.py
pycroglia/core/errors/__init__.py
pycroglia/core/errors/errors.py
pycroglia/core/io/__init__.py
pycroglia/core/io/output.py
pycroglia/core/io/readers.py
pycroglia/core/io/tests/__init__.py
pycroglia/core/io/tests/unit/__init__.py
pycroglia/core/io/tests/unit/test_output.py
pycroglia/core/io/tests/unit/test_readers.py
pycroglia/core/plot/__init__.py
pycroglia/core/plot/branch.py
pycroglia/core/plot/endpoints.py
pycroglia/core/plot/full_cell_analysis.py
pycroglia/core/plot/original_cell.py
pycroglia/core/plot/skeleton.py
pycroglia/core/skeletonize/__init__.py
pycroglia/core/skeletonize/msfm.py
pycroglia/core/skeletonize/shortest_path.py
pycroglia/core/skeletonize/skeleton.py
pycroglia/core/skeletonize/raytracing/__init__.py
pycroglia/core/skeletonize/raytracing/euler.py
pycroglia/core/skeletonize/raytracing/factory.py
pycroglia/core/skeletonize/raytracing/rk4.py
pycroglia/core/skeletonize/raytracing/simple.py
pycroglia/core/skeletonize/raytracing/stepper.py
pycroglia/core/skeletonize/tests/__init__.py
pycroglia/core/skeletonize/tests/unit/__init__.py
pycroglia-0.0.5.dist-info/licenses/LICENSE
pycroglia-0.0.5.dist-info/METADATA
pycroglia-0.0.5.dist-info/WHEEL
pycroglia-0.0.5.dist-info/entry_points.txt
pycroglia-0.0.5.dist-info/top_level.txt
pycroglia-0.0.5.dist-info/RECORD
