Metadata-Version: 2.4
Name: pycroglia
Version: 0.0.5
Summary: Software for isolating and analyzing microglial morphology.
Requires-Python: >=3.10
License-File: LICENSE
Requires-Dist: numpy>=2.2.6
Requires-Dist: opencv-python>=4.11.0.86
Requires-Dist: pyqt6>=6.9.1
Requires-Dist: pyqtgraph>=0.13.7
Requires-Dist: scipy>=1.15.3
Requires-Dist: scikit-image>=0.25.2
Requires-Dist: scikit-learn>=1.7.1
Requires-Dist: tifffile>=2025.5.10
Requires-Dist: openpyxl>=3.1.5
Requires-Dist: pyvista>=0.46.4
Provides-Extra: docs
Requires-Dist: sphinx>=7.2; extra == "docs"
Requires-Dist: sphinx-rtd-theme>=2.0; extra == "docs"
Requires-Dist: myst-parser>=2.0; extra == "docs"
Requires-Dist: sphinxcontrib-mermaid>=0.9; extra == "docs"
Requires-Dist: sphinx-autobuild>=2024.10.3; extra == "docs"
Dynamic: license-file
